Workbook

Sheet 00_Home
A1: PROJECT AURA · AI-Powered Project Management
A2: ABC Retail Corporation — GenAI Customer Analytics Platform
A4: PROJECT SUMMARY | E4: PROJECT HEALTH
A5: Project Name | B5: ABC Retail Corporation — AI Customer Analytics | E5: Overall Status | F5: AMBER — review milestone tracker
A6: Client | B6: ABC Retail Corporation | E6: Schedule | F6: AMBER — update actuals in Task Plan
A7: Service Provider | B7: XYZ Technology Solutions | E7: Budget | F7: GREEN — update in Budget Tracker
A8: Project Type | B8: GenAI / AI Implementation | E8: Resources | F8: AMBER — all at 100%, review allocation
A9: Delivery Model | B9: Fixed Price | E9: Risks | F9: RED — 6 open risks, none mitigated
A10: Start Date | B10: 46211
A11: End Date | B11: 46323
A12: Duration | B12: 16 weeks
A13: Team Size | B13: 5
A14: PM
A15: Last Updated | B15: 46222
A17: NAVIGATION
A18: 01_Executive_Dashboard | B18: Executive KPIs, budget burn, schedule health
A19: 02_Project_Charter | B19: Project scope, objectives, assumptions, constraints
A20: 03_Detailed_Task_Plan | B20: WBS task list with actuals, dependencies, % complete
A21: 04_Budget_Tracker | B21: Cost plan vs actuals, burn rate, variance ← NEW
A22: 05_Milestone_Tracker | B22: Key milestones with RAG status and variance
A23: 06_Resource_Plan | B23: Weekly allocation, utilisation flags
A24: 07_RAID_Register | B24: Risks, Assumptions, Issues, Dependencies
A25: 08_RACI_Matrix | B25: Responsibility assignments
A26: 09_Weekly_Status | B26: Weekly status reports (fill every Friday) ← NEW
A27: 10_Change_Log | B27: Scope, schedule, budget change requests ← NEW

Sheet Executive_Dashboard
A1: EXECUTIVE PROJECT DASHBOARD
A3: KEY METRICS
A4: Schedule % | C4: Budget Burn % | E4: Milestones Done | G4: Open Risks | I4: Open Issues
A5: =IFERROR(COUNTIF(Detailed_Task_Plan!K4:K200,"Done")/COUNTIF(Detailed_Task_Plan!K4:K200,"<>"),0) -> 0 | C5: =IFERROR(Budget_Tracker!G14/Budget_Tracker!E14,0) -> 0 | E5: =COUNTIF(Milestone_Tracker!F4:F20,"Complete") -> 0 | G5: =COUNTIF(RAID_Register!H4:H50,"Open") -> 0 | I5: =COUNTIF(RAID_Register!H54:H100,"Open") -> 0
A7: PHASE SUMMARY
A8: Phase | B8: Start | C8: End | D8: Duration | E8: Owner | F8: Status | G8: % Complete | H8: RAG
A9: Initiation | B9: 2026-07-08 | C9: 2026-07-15 | D9: 1w | E9: PM | F9: Planned | G9: 0% | H9: AMBER
A10: Discovery | B10: 2026-07-15 | C10: 2026-07-29 | D10: 2w | E10: BA | F10: Planned | G10: 0% | H10: AMBER
A11: Design | B11: 2026-07-29 | C11: 2026-08-12 | D11: 2w | E11: Architect | F11: Planned | G11: 0% | H11: AMBER
A12: Development | B12: 2026-08-12 | C12: 2026-09-16 | D12: 5w | E12: Dev Lead | F12: Planned | G12: 0% | H12: AMBER
A13: Testing | B13: 2026-09-16 | C13: 2026-09-30 | D13: 2w | E13: QA Lead | F13: Planned | G13: 0% | H13: AMBER
A14: UAT | B14: 2026-09-30 | C14: 2026-10-07 | D14: 1w | E14: Client PM | F14: Planned | G14: 0% | H14: AMBER
A15: Deployment | B15: 2026-10-07 | C15: 2026-10-14 | D15: 1w | E15: DevOps | F15: Planned | G15: 0% | H15: AMBER
A16: Hypercare | B16: 2026-10-14 | C16: 2026-10-28 | D16: 2w | E16: PM | F16: Planned | G16: 0% | H16: AMBER
A18: TOP RISKS (from RAID Register)
A19: ID | B19: Description | C19: Impact | D19: Probability | E19: Score | F19: Owner | G19: Mitigation | H19: Status
A20: =RAID_Register!A4 -> ID | B20: =RAID_Register!B4 -> Type | C20: =RAID_Register!C4 -> Description | D20: =RAID_Register!D4 -> Impact (1-5) | E20: =IFERROR(RAID_Register!C4*RAID_Register!D4,"") | F20: =RAID_Register!F4 -> Risk Score | G20: =RAID_Register!G4 -> Owner | H20: =RAID_Register!H4 -> Mitigation / Action
A21: =RAID_Register!A5 -> R1 | B21: =RAID_Register!B5 -> Risk | C21: =RAID_Register!C5 -> Requirement scope creep — client adds features mid-sprint | D21: =RAID_Register!D5 -> 4 | E21: =IFERROR(RAID_Register!C5*RAID_Register!D5,"") | F21: =RAID_Register!F5 -> 12 | G21: =RAID_Register!G5 -> PM | H21: =RAID_Register!H5 -> Conduct detailed requirements workshops; freeze scope after sign-off (Week 2). All changes go through formal change request.
A22: =RAID_Register!A6 -> R2 | B22: =RAID_Register!B6 -> Risk | C22: =RAID_Register!C6 -> Integration failures with existing retail data systems | D22: =RAID_Register!D6 -> 4 | E22: =IFERROR(RAID_Register!C6*RAID_Register!D6,"") | F22: =RAID_Register!F6 -> 12 | G22: =RAID_Register!G6 -> Tech Lead | H22: =RAID_Register!H6 -> Define API contracts in Week 3. Run integration smoke tests in each sprint. Maintain a fallback data-sync approach.
A23: =RAID_Register!A7 -> R3 | B23: =RAID_Register!B7 -> Risk | C23: =RAID_Register!C7 -> AI model performance below 85% accuracy threshold | D23: =RAID_Register!D7 -> 5 | E23: =IFERROR(RAID_Register!C7*RAID_Register!D7,"") | F23: =RAID_Register!F7 -> 10 | G23: =RAID_Register!G7 -> Dev Lead | H23: =RAID_Register!H7 -> Run baseline model benchmarks in Discovery. Allocate 1 extra sprint buffer for model tuning if needed.
A24: =RAID_Register!A8 -> R4 | B24: =RAID_Register!B8 -> Risk | C24: =RAID_Register!C8 -> Security vulnerabilities in AI API endpoints | D24: =RAID_Register!D8 -> 5 | E24: =IFERROR(RAID_Register!C8*RAID_Register!D8,"") | F24: =RAID_Register!F8 -> 10 | G24: =RAID_Register!G8 -> DevOps | H24: =RAID_Register!H8 -> Include security audit in testing phase (Week 11). Follow OWASP API security checklist. Penetration test before UAT.
A25: =RAID_Register!A9 -> R5 | B25: =RAID_Register!B9 -> Risk | C25: =RAID_Register!C9 -> Client data delivery delays blocking development | D25: =RAID_Register!D9 -> 4 | E25: =IFERROR(RAID_Register!C9*RAID_Register!D9,"") | F25: =RAID_Register!F9 -> 12 | G25: =RAID_Register!G9 -> PM | H25: =RAID_Register!H9 -> Formally request data assets in Week 1. Escalate to sponsor if not received by Week 3.

Sheet Detailed_Task_Plan
A1: DETAILED TASK PLAN (WBS)
A2: Blue cells = fill in | Green cells = formula (do not edit) | Status dropdown: Not Started / In Progress / Done / On Hold / Cancelled
A3: WBS | B3: Phase | C3: Task / Deliverable | D3: Owner | E3: Predecessor | F3: Planned Start | G3: Planned End | H3: Actual Start | I3: Actual End | J3: Planned Days | K3: Actual Days | L3: % Complete | M3: Status | N3: Comments
A4: 1.0 | B4: Initiation | C4: Project kickoff | D4: PM | F4: 2026-07-08 | G4: 2026-07-15 | J4: =IFERROR(DATEDIF(F4,G4,"D"),"") -> 7 | K4: =IFERROR(DATEDIF(H4,I4,"D"),"") -> 0 | L4: 0% | M4: Not Started
A5: 1.1 | B5: Initiation | C5: Project charter sign-off | D5: PM | E5: 1.0 | F5: 2026-07-08 | G5: 2026-07-12 | J5: =IFERROR(DATEDIF(F5,G5,"D"),"") -> 4 | K5: =IFERROR(DATEDIF(H5,I5,"D"),"") -> 0 | L5: 0% | M5: Not Started
A6: 1.2 | B6: Initiation | C6: Stakeholder register | D6: PM | E6: 1.0 | F6: 2026-07-08 | G6: 2026-07-15 | J6: =IFERROR(DATEDIF(F6,G6,"D"),"") -> 7 | K6: =IFERROR(DATEDIF(H6,I6,"D"),"") -> 0 | L6: 0% | M6: Not Started
A7: 2.0 | B7: Discovery | C7: Requirements gathering | D7: BA | E7: 1.0 | F7: 2026-07-15 | G7: 2026-07-29 | J7: =IFERROR(DATEDIF(F7,G7,"D"),"") -> 14 | K7: =IFERROR(DATEDIF(H7,I7,"D"),"") -> 0 | L7: 0% | M7: Not Started
A8: 2.1 | B8: Discovery | C8: Current-state data assessment | D8: BA | E8: 1.1 | F8: 2026-07-15 | G8: 2026-07-22 | J8: =IFERROR(DATEDIF(F8,G8,"D"),"") -> 7 | K8: =IFERROR(DATEDIF(H8,I8,"D"),"") -> 0 | L8: 0% | M8: Not Started
A9: 2.2 | B9: Discovery | C9: AI use-case definition | D9: BA | E9: 2.1 | F9: 2026-07-22 | G9: 2026-07-29 | J9: =IFERROR(DATEDIF(F9,G9,"D"),"") -> 7 | K9: =IFERROR(DATEDIF(H9,I9,"D"),"") -> 0 | L9: 0% | M9: Not Started
A10: 2.3 | B10: Discovery | C10: Requirements doc sign-off | D10: Client PM | E10: 2.2 | F10: 2026-07-29 | G10: 2026-07-29 | J10: =IFERROR(DATEDIF(F10,G10,"D"),"") -> 0 | K10: =IFERROR(DATEDIF(H10,I10,"D"),"") -> 0 | L10: 0% | M10: Not Started
A11: 3.0 | B11: Design | C11: Solution architecture | D11: Architect | E11: 2.0 | F11: 2026-07-29 | G11: 2026-08-12 | J11: =IFERROR(DATEDIF(F11,G11,"D"),"") -> 14 | K11: =IFERROR(DATEDIF(H11,I11,"D"),"") -> 0 | L11: 0% | M11: Not Started
A12: 3.1 | B12: Design | C12: Data pipeline design | D12: Architect | E12: 2.2 | F12: 2026-07-29 | G12: 2026-08-05 | J12: =IFERROR(DATEDIF(F12,G12,"D"),"") -> 7 | K12: =IFERROR(DATEDIF(H12,I12,"D"),"") -> 0 | L12: 0% | M12: Not Started
A13: 3.2 | B13: Design | C13: AI model selection & design | D13: Architect | E13: 2.2 | F13: 2026-07-29 | G13: 2026-08-05 | J13: =IFERROR(DATEDIF(F13,G13,"D"),"") -> 7 | K13: =IFERROR(DATEDIF(H13,I13,"D"),"") -> 0 | L13: 0% | M13: Not Started
A14: 3.3 | B14: Design | C14: API contract definition | D14: Tech Lead | E14: 3.1 | F14: 2026-08-05 | G14: 2026-08-12 | J14: =IFERROR(DATEDIF(F14,G14,"D"),"") -> 7 | K14: =IFERROR(DATEDIF(H14,I14,"D"),"") -> 0 | L14: 0% | M14: Not Started
A15: 3.4 | B15: Design | C15: Design spec sign-off | D15: Client PM | E15: 3.3 | F15: 2026-08-12 | G15: 2026-08-12 | J15: =IFERROR(DATEDIF(F15,G15,"D"),"") -> 0 | K15: =IFERROR(DATEDIF(H15,I15,"D"),"") -> 0 | L15: 0% | M15: Not Started
A16: 4.0 | B16: Development | C16: Core development | D16: Dev Lead | E16: 3.0 | F16: 2026-08-12 | G16: 2026-09-16 | J16: =IFERROR(DATEDIF(F16,G16,"D"),"") -> 35 | K16: =IFERROR(DATEDIF(H16,I16,"D"),"") -> 0 | L16: 0% | M16: Not Started
... A37: 8.3 | B37: Hypercare | C37: Project closure report | D37: PM | E37: 8.2 | F37: 2026-10-28 | G37: 2026-10-28 | J37: =IFERROR(DATEDIF(F37,G37,"D"),"") -> 0 | K37: =IFERROR(DATEDIF(H37,I37,"D"),"") -> 0 | L37: 0% | M37: Not Started

Sheet Budget_Tracker
A1: BUDGET TRACKER · NEW
A3: CONTRACT SUMMARY
A4: Total Contract Value ($) | B4: 250000 | C4: ← update this
A5: Contingency Reserve ($) | B5: 25000 | C5: ← typical 10%
A6: Baseline Budget ($) | B6: =B4-B5 -> 225000
A8: RESOURCE COST PLAN vs ACTUALS
A9: Resource | B9: Role | C9: Daily Rate ($) | D9: Planned Days | E9: Planned Cost ($) | F9: Actual Days | G9: Actual Cost ($) | H9: Variance ($) | I9: Variance %
A10: PM_1 | B10: PM | C10: 650 | D10: 80 | E10: =C10*D10 -> 52000 | F10: 0 | G10: =C10*F10 -> 0 | H10: =E10-G10 -> 52000 | I10: =IFERROR(H10/E10,0) -> 1
A11: TechLead_1 | B11: Tech Lead | C11: 750 | D11: 80 | E11: =C11*D11 -> 60000 | F11: 0 | G11: =C11*F11 -> 0 | H11: =E11-G11 -> 60000 | I11: =IFERROR(H11/E11,0) -> 1
A12: Developer_1 | B12: Developer | C12: 600 | D12: 80 | E12: =C12*D12 -> 48000 | F12: 0 | G12: =C12*F12 -> 0 | H12: =E12-G12 -> 48000 | I12: =IFERROR(H12/E12,0) -> 1
A13: QAEngineer_1 | B13: QA Engineer | C13: 550 | D13: 60 | E13: =C13*D13 -> 33000 | F13: 0 | G13: =C13*F13 -> 0 | H13: =E13-G13 -> 33000 | I13: =IFERROR(H13/E13,0) -> 1
A14: DevOps_1 | B14: DevOps | C14: 650 | D14: 50 | E14: =C14*D14 -> 32500 | F14: 0 | G14: =C14*F14 -> 0 | H14: =E14-G14 -> 32500 | I14: =IFERROR(H14/E14,0) -> 1
A15: TOTALS | D15: =SUM(D10:D14) -> 350 | E15: =SUM(E10:E14) -> 225500 | F15: =SUM(F10:F14) -> 0 | G15: =SUM(G10:G14) -> 0 | H15: =SUM(H10:H14) -> 225500 | I15: =IFERROR(H15/E15,0) -> 1
A17: BURN RATE SUMMARY
A18: Total Planned Cost ($) | B18: =E15 -> 225500
A19: Total Actual Cost ($) | B19: =G15 -> 0
A20: Cost Variance ($) | B20: =E18-E19 -> 0
A21: Budget Burn % | B21: =IFERROR(E19/B6,0) -> 0
A22: Remaining Budget ($) | B22: =B6-E19 -> 225000

Sheet Milestone_Tracker
A1: MILESTONE TRACKER
A2: ID | B2: Milestone | C2: Owner | D2: Planned Date | E2: Actual Date | F2: Status | G2: Priority | H2: Days Variance | I2: Remarks
A3: M1 | B3: Project Kickoff | C3: PM | D3: 2026-07-08 | F3: Complete | G3: High | H3: =IFERROR(IF(E3="","",DATEDIF(D3,E3,"D")),"")
A4: M2 | B4: Requirements Sign-off | C4: BA | D4: 2026-07-29 | F4: Planned | G4: High | H4: =IFERROR(IF(E4="","",DATEDIF(D4,E4,"D")),"")
A5: M3 | B5: Design Review & Approval | C5: Architect | D5: 2026-08-12 | F5: Planned | G5: High | H5: =IFERROR(IF(E5="","",DATEDIF(D5,E5,"D")),"")
A6: M4 | B6: Development Complete | C6: Dev Lead | D6: 2026-09-16 | F6: Planned | G6: High | H6: =IFERROR(IF(E6="","",DATEDIF(D6,E6,"D")),"")
A7: M5 | B7: QA Testing Complete | C7: QA Lead | D7: 2026-09-30 | F7: Planned | G7: High | H7: =IFERROR(IF(E7="","",DATEDIF(D7,E7,"D")),"")
A8: M6 | B8: UAT Sign-off | C8: Client PM | D8: 2026-10-07 | F8: Planned | G8: High | H8: =IFERROR(IF(E8="","",DATEDIF(D8,E8,"D")),"")
A9: M7 | B9: Go-Live | C9: DevOps | D9: 2026-10-14 | F9: Planned | G9: Critical | H9: =IFERROR(IF(E9="","",DATEDIF(D9,E9,"D")),"")
A10: M8 | B10: Hypercare Complete | C10: PM | D10: 2026-10-28 | F10: Planned | G10: Medium | H10: =IFERROR(IF(E10="","",DATEDIF(D10,E10,"D")),"")

Sheet Resource_Plan
A1: RESOURCE PLAN · Weekly Allocation
A2: Resource | B2: Role | C2: Dept | D2: Start Date | E2: End Date | F2: Planned Hrs | G2: Actual Hrs | H2: Allocation % | I2: Utilisation % | J2: Flag
A3: PM_1 | B3: PM | C3: Delivery | D3: 2026-07-08 | E3: 2026-10-28 | F3: 480 | G3: 0 | H3: 80% | I3: =IFERROR(G3/F3,0) -> 0 | J3: =IF(IFERROR(VALUE(LEFT(H3,LEN(H3)-1)),0)>90,"OVERLOADED","OK") -> OK
A4: TechLead_1 | B4: Tech Lead | C4: Engineering | D4: 2026-07-08 | E4: 2026-10-28 | F4: 480 | G4: 0 | H4: 80% | I4: =IFERROR(G4/F4,0) -> 0 | J4: =IF(IFERROR(VALUE(LEFT(H4,LEN(H4)-1)),0)>90,"OVERLOADED","OK") -> OK
A5: Developer_1 | B5: Developer | C5: Engineering | D5: 2026-07-08 | E5: 2026-10-28 | F5: 480 | G5: 0 | H5: 80% | I5: =IFERROR(G5/F5,0) -> 0 | J5: =IF(IFERROR(VALUE(LEFT(H5,LEN(H5)-1)),0)>90,"OVERLOADED","OK") -> OK
A6: QAEngineer_1 | B6: QA Engineer | C6: Quality | D6: 2026-07-08 | E6: 2026-10-28 | F6: 360 | G6: 0 | H6: 80% | I6: =IFERROR(G6/F6,0) -> 0 | J6: =IF(IFERROR(VALUE(LEFT(H6,LEN(H6)-1)),0)>90,"OVERLOADED","OK") -> OK
A7: DevOps_1 | B7: DevOps | C7: Engineering | D7: 2026-07-08 | E7: 2026-10-28 | F7: 300 | G7: 0 | H7: 80% | I7: =IFERROR(G7/F7,0) -> 0 | J7: =IF(IFERROR(VALUE(LEFT(H7,LEN(H7)-1)),0)>90,"OVERLOADED","OK") -> OK
A9: Note: Max recommended allocation is 80% to allow for meetings, admin, and leave. Flag highlights resources >90%.

Sheet RAID_Register
A1: RAID REGISTER · Risks · Assumptions · Issues · Dependencies
A3: RISKS
A4: ID | B4: Type | C4: Description | D4: Impact (1-5) | E4: Probability (1-5) | F4: Risk Score | G4: Owner | H4: Mitigation / Action | I4: Status
A5: R1 | B5: Risk | C5: Requirement scope creep — client adds features mid-sprint | D5: 4 | E5: 3 | F5: =IF(D5="","",D5*E5) -> 12 | G5: PM | H5: Conduct detailed requirements workshops; freeze scope after sign-off (Week 2). All changes go through formal change request. | I5: Open
A6: R2 | B6: Risk | C6: Integration failures with existing retail data systems | D6: 4 | E6: 3 | F6: =IF(D6="","",D6*E6) -> 12 | G6: Tech Lead | H6: Define API contracts in Week 3. Run integration smoke tests in each sprint. Maintain a fallback data-sync approach. | I6: Open
A7: R3 | B7: Risk | C7: AI model performance below 85% accuracy threshold | D7: 5 | E7: 2 | F7: =IF(D7="","",D7*E7) -> 10 | G7: Dev Lead | H7: Run baseline model benchmarks in Discovery. Allocate 1 extra sprint buffer for model tuning if needed. | I7: Open
A8: R4 | B8: Risk | C8: Security vulnerabilities in AI API endpoints | D8: 5 | E8: 2 | F8: =IF(D8="","",D8*E8) -> 10 | G8: DevOps | H8: Include security audit in testing phase (Week 11). Follow OWASP API security checklist. Penetration test before UAT. | I8: Open
A9: R5 | B9: Risk | C9: Client data delivery delays blocking development | D9: 4 | E9: 3 | F9: =IF(D9="","",D9*E9) -> 12 | G9: PM | H9: Formally request data assets in Week 1. Escalate to sponsor if not received by Week 3. | I9: Open
A10: R6 | B10: Risk | C10: Testing coverage gaps leading to production defects | D10: 4 | E10: 2 | F10: =IF(D10="","",D10*E10) -> 8 | G10: QA Lead | H10: Develop test plan with 90% coverage target. Automate regression suite. Include performance and load tests. | I10: Open
A12: ASSUMPTIONS
A13: ID | B13: Type | C13: Description | D13: Impact (1-5) | E13: Probability (1-5) | F13: Risk Score | G13: Owner | H13: Mitigation / Action | I13: Status
A14: A1 | B14: Assumption | C14: Client will provide access to production data environment by end of Week 2 | D14: 3 | E14: 2 | F14: =IF(D14="","",D14*E14) -> 6 | G14: PM | H14: Confirm in kickoff meeting. Raise as issue if not received by 2026-07-22. | I14: Open
A15: A2 | B15: Assumption | C15: API schema and documentation are available and stable at project start | D15: 3 | E15: 3 | F15: =IF(D15="","",D15*E15) -> 9 | G15: Tech Lead | H15: Validate in Discovery. Raise as issue immediately if schema is incomplete. | I15: Open
A16: A3 | B16: Assumption | C16: Client product owner available minimum 4 hrs/week for reviews and approvals | D16: 4 | E16: 2 | F16: =IF(D16="","",D16*E16) -> 8 | G16: PM | H16: Confirm availability in kickoff. Include in project charter sign-off. | I16: Open
A17: A4 | B17: Assumption | C17: Staging environment mirrors production; no major config differences | D17: 4 | E17: 2 | F17: =IF(D17="","",D17*E17) -> 8 | G17: DevOps | H17: Conduct environment audit in Week 1. Document any deltas. | I17: Open
A18: A5 | B18: Assumption | C18: Client responds to review and sign-off requests within 3 business days | D18: 4 | E18: 3 | F18: =IF(D18="","",D18*E18) -> 12 | G18: PM | H18: Include SLA in project charter. Track in weekly status report. | I18: Open
A20: ISSUES
A21: ID | B21: Type | C21: Description | D21: Impact (1-5) | E21: Probability (1-5) | F21: Risk Score | G21: Owner | H21: Mitigation / Action | I21: Status
A22: I1 | B22: Issue | C22: [Add issues here as they arise] | D22: 0 | E22: 0 | F22: =IF(D22="","",D22*E22) -> 0 | G22: TBD | H22: [Add mitigation action] | I22: Open
A24: DEPENDENCIES
A25: ID | B25: Type | C25: Description | D25: Impact (1-5) | E25: Probability (1-5) | F25: Risk Score | G25: Owner | H25: Mitigation / Action | I25: Status
A26: D1 | B26: Dependency | C26: Client data team must deliver cleaned dataset before AI model training (Week 4) | D26: 4 | E26: 3 | F26: =IF(D26="","",D26*E26) -> 12 | G26: BA | H26: Confirm data readiness date with client in Week 1. Monitor weekly. | I26: Open
A27: D2 | B27: Dependency | C27: Client IT must provision staging environment before development begins (Week 2) | D27: 4 | E27: 3 | F27: =IF(D27="","",D27*E27) -> 12 | G27: DevOps | H27: Request provisioning in kickoff. Chase weekly if not received by Week 2. | I27: Open
A28: D3 | B28: Dependency | C28: Third-party AI platform licence must be procured before model training (Week 3) | D28: 3 | E28: 2 | F28: =IF(D28="","",D28*E28) -> 6 | G28: PM | H28: Raise purchase request in Week 1 to avoid procurement delays. | I28: Open

Sheet RACI_Matrix
A1: RACI MATRIX · Responsible · Accountable · Consulted · Informed
A2: R = Responsible — does the work | C2: A = Accountable — final authority | E2: C = Consulted — provides input | G2: I = Informed — kept in the loop
A4: Activity | B4: PM | C4: BA | D4: Architect | E4: Dev Lead | F4: QA Lead | G4: DevOps | H4: Client PM
A5: Project Kickoff | B5: A | C5: C | D5: C | E5: C | F5: C | G5: I | H5: C
A6: Requirements Gathering | B6: A | C6: R | D6: C | E6: C | F6: C | G6: I | H6: C
A7: Solution Architecture | B7: I | C7: C | D7: R | E7: C | F7: I | G7: C | H7: A
A8: Project Plan Approval | B8: A | C8: I | D8: I | E8: I | F8: I | G8: I | H8: C
A9: Data Pipeline Development | B9: I | C9: C | D9: C | E9: R | F9: I | G9: C | H9: I
A10: AI Model Development | B10: I | C10: C | D10: A | E10: R | F10: I | G10: C | H10: I
A11: API Development | B11: I | C11: I | D11: C | E11: R | F11: I | G11: C | H11: I
A12: Code Review | B12: I | C12: I | D12: A | E12: R | F12: C | G12: C | H12: I
A13: Test Plan Creation | B13: I | C13: C | D13: C | E13: C | F13: R | G13: C | H13: A
A14: QA Testing Execution | B14: I | C14: I | D14: C | E14: C | F14: R | G14: C | H14: I
A15: Security Audit | B15: I | C15: I | D15: C | E15: C | F15: C | G15: R | H15: I
... A28: Project Closure Report | B28: R | C28: C | D28: I | E28: I | F28: I | G28: I | H28: A

Sheet Change_Log
A1: CHANGE LOG · Record all scope, schedule, and budget changes
A2: Every change to scope, timeline, or budget must be logged here and approved before implementation.
A3: CR # | B3: Date Raised | C3: Raised By | D3: Type | E3: Description | F3: Impact on Schedule | G3: Impact on Budget ($) | H3: Approved By | I3: Approval Date | J3: Status | K3: New Baseline Date
A4: CR-001 | B4: 2026-07-08 | C4: PM | D4: Scope | E4: [Example] Add real-time dashboard refresh | F4: 0 days | G4: $0 | H4: Sponsor | I4: 2026-07-10 | J4: Approved | K4: 2026-07-08
